blocktrace/__init__.py
blocktrace/blocktrace.py
blocktrace-0.0.16.dist-info/LICENSE
blocktrace-0.0.16.dist-info/METADATA
blocktrace-0.0.16.dist-info/WHEEL
blocktrace-0.0.16.dist-info/top_level.txt
blocktrace-0.0.16.dist-info/RECORD
